{
	"invoice": [
		{
			"id": "000096",
			"date": "8 jun",
			"projects": "Blue-breasted cordon bleu",
			"client": "Oyondu",
			"due_date": "4/15/2022",
			"amount": "19476.65",
			"status": "",
			"orden": "1"
		},
		{
			"id": "000097",
			"date": "30 ene",
			"projects": "Goose, canada",
			"client": "Zoombox",
			"due_date": "6/19/2022",
			"amount": "6809.21",
			"status": "draft",
			"orden": "2"
		},
		{
			"id": "000098",
			"date": "26 abr",
			"projects": "Coyote",
			"client": "Jetpulse",
			"due_date": "7/19/2022",
			"amount": "19476.98",
			"status": "Pending",
			"orden": "3"
		},
		{
			"id": "000099",
			"date": "11 jul",
			"projects": "Racer, blue",
			"client": "Cogibox",
			"due_date": "8/19/2022",
			"amount": "5773.37",
			"status": "Pending",
			"orden": "4"
		},
		{
			"id": "00009a",
			"date": "13 may",
			"projects": "Ibis, glossy",
			"client": "Chatterpoint",
			"due_date": "1/14/2022",
			"amount": "25331.45",
			"status": "paid",
			"orden": "5"
		},
		{
			"id": "00009b",
			"date": "21 ago",
			"projects": "Black swan",
			"client": "Buzzshare",
			"due_date": "7/19/2022",
			"amount": "20942.91",
			"status": "draft",
			"orden": "6"
		},
		{
			"id": "00009c",
			"date": "21 ago",
			"projects": "Horned puffin",
			"client": "Divavu",
			"due_date": "12/12/2021",
			"amount": "25619.72",
			"status": "draft",
			"orden": "7"
		},
		{
			"id": "00009d",
			"date": "3 oct",
			"projects": "Mongoose, yellow",
			"client": "Skilith",
			"due_date": "5/24/2022",
			"amount": "28799.51",
			"status": "paid",
			"orden": "8"
		},
		{
			"id": "00009e",
			"date": "30 mar",
			"projects": "Lion, california sea",
			"client": "Camimbo",
			"due_date": "9/24/2022",
			"amount": "11725.61",
			"status": "",
			"orden": "9"
		},
		{
			"id": "00009f",
			"date": " 10 ene",
			"projects": "Buffalo, american",
			"client": "Topicblab",
			"due_date": "10/31/2021",
			"amount": "16386.55",
			"status": "",
			"orden": "1"
		}
	],
	"profile": [
		{
			"id": 1,
			"address": "Calle Juan Martín",
			"type": "frutería",
			"nombre": "Lola Castro Frutas",
			"latitude": 37.880273,
			"longitude": -4.792098
		},
		{
			"id": 2,
			"address": "Calle Pepe Cruz",
			"type": "supermercado",
			"nombre": "Ultramarinos Lolo Castro",
			"latitude": 37.862323,
			"longitude": -4.77812
		},
		{
			"id": 3,
			"address": "Avenida de la Cruz",
			"type": "pescadería",
			"nombre": "Pescados El Boquerón",
			"latitude": 37.856273,
			"longitude": -4.776992
		}
	],
	"categories": [
		{
			"id": 0,
			"name": "All"
		},
		{
			"id": 1,
			"name": "Movies",
			"subcat": [
				{
					"id": 10,
					"name": "DVD"
				},
				{
					"id": 11,
					"name": "BluRay"
				},
				{
					"id": 12,
					"name": "Download"
				}
			]
		},
		{
			"id": 2,
			"name": "Games",
			"subcat": [
				{
					"id": 20,
					"name": "XBox"
				},
				{
					"id": 21,
					"name": "PC",
					"subcat": [
						{
							"id": 210,
							"name": "action"
						},
						{
							"id": 211,
							"name": "sport"
						},
						{
							"id": 212,
							"name": "moshi moshi",
							"subcat": [
								{
									"id": 2120,
									"name": "xxx"
								},
								{
									"id": 2121,
									"name": "tanke moshi"
								},
								{
									"id": 2122,
									"name": "xtreme Moshi"
								}
							]
						}
					]
				}
			]
		},
		{
			"id": 3,
			"name": "Music"
		}
	]
}